{
  "MicrosoftAuthLogin": {},
  "Derp": {
    "Spiny": true,
    "Increment": 39.62592697143555,
    "Fake Derp": true
  },
  "ClickGUI": {},
  "FreeCam": {},
  "SnapLook": {},
  "FreeLook": {},
  "HUD": {},
  "CPS": {
    "posX": 183.0,
    "posY": 136.0,
    "HorizontalFacing": "Free",
    "VerticalFacing": "Free",
    "Show Background": true
  },
  "FPS": {
    "posX": 521.0,
    "posY": 126.0,
    "HorizontalFacing": "Free",
    "VerticalFacing": "Free",
    "Show Background": true
  },
  "MusicPlayer": {},
  "MusicOverlay": {},
  "MotionBlur": {
    "FrameMultiplier": 1.9225757122039795
  },
  "Rotations": {
    "Silent": true
  },
  "KeyStrokes": {
    "posX": 14.0,
    "posY": 197.0,
    "HorizontalFacing": "Free",
    "VerticalFacing": "Free"
  },
  "TabGUI": {
    "posX": 16.0,
    "posY": 97.0,
    "HorizontalFacing": "Free",
    "VerticalFacing": "Free"
  },
  "ArmorStatus": {
    "posX": 0.0,
    "posY": 0.0,
    "HorizontalFacing": "Right",
    "VerticalFacing": "Bottom"
  },
  "KillAura": {
    "Priority": "Distance",
    "Range": 8.0,
    "AutoBlock": false,
    "CPS": 20.0,
    "PlayerOnly": false,
    "Team": false,
    "AttackInvisibleEntity": true
  },
  "Criticals": {},
  "AntiInvisible": {}
}